ckpt_manager/__init__.py
ckpt_manager/ckpt_manager.py
pytorch_ckpt_manager-0.1.3.dist-info/LICENSE
pytorch_ckpt_manager-0.1.3.dist-info/METADATA
pytorch_ckpt_manager-0.1.3.dist-info/WHEEL
pytorch_ckpt_manager-0.1.3.dist-info/top_level.txt
pytorch_ckpt_manager-0.1.3.dist-info/RECORD
