Metadata-Version: 2.1
Name: pytorch-ckpt-manager
Version: 0.1.3
Summary: A simple PyTorch checkpoint manager
Home-page: UNKNOWN
Author: Ovikx
License: UNKNOWN
Project-URL: Source code, https://github.com/Ovikx/PyTorch-Checkpoint-Manager
Platform: UNKNOWN
Classifier: Programming Language :: Python :: 3
Classifier: License :: OSI Approved :: MIT License
Classifier: Operating System :: OS Independent
Requires-Python: >=3.7
License-File: LICENSE
Requires-Dist: torch
